mcfa/__init__.py
mcfa/core.py
mcfa/figures.py
mcfa-0.1.6.dist-info/LICENSE
mcfa-0.1.6.dist-info/METADATA
mcfa-0.1.6.dist-info/WHEEL
mcfa-0.1.6.dist-info/RECORD
