Metadata-Version: 2.1
Name: mcfa
Version: 0.1.6
Summary: Mixtures of Common Factor Analyzers with missing data
Home-page: https://github.com/maxmahlke/mcfa.git
License: MIT
Author: Max Mahlke
Author-email: max.mahlke@oca.eu
Requires-Python: >=3.8
Classifier: License :: OSI Approved :: MIT License
Classifier: Programming Language :: Python :: 3
Classifier: Programming Language :: Python :: 3.8
Classifier: Programming Language :: Python :: 3.9
Classifier: Programming Language :: Python :: 3.10
Classifier: Programming Language :: Python :: 3.11
Classifier: Programming Language :: Python :: 3.12
Classifier: Programming Language :: Python :: 3.13
Requires-Dist: matplotlib (>=3)
Requires-Dist: numpy (>=1)
Requires-Dist: pandas (>=2)
Requires-Dist: pyppca (>=0.0.4)
Requires-Dist: scikit-learn (>=1.2.1)
Requires-Dist: tensorflow (>=2)
Requires-Dist: tensorflow-probability (>=0.21.0,<1)
Requires-Dist: tqdm (>=4)
Project-URL: Documentation, https://github.com/maxmahlke/mcfa.git
Project-URL: Repository, https://github.com/maxmahlke/mcfa.git
